odoo/addons/account_banking_ach_discount/README.rst
odoo/addons/account_banking_ach_discount/__init__.py
odoo/addons/account_banking_ach_discount/__manifest__.py
odoo/addons/account_banking_ach_discount/i18n/account_banking_ach_discount.pot
odoo/addons/account_banking_ach_discount/models/__init__.py
odoo/addons/account_banking_ach_discount/models/account_move.py
odoo/addons/account_banking_ach_discount/models/account_move_line.py
odoo/addons/account_banking_ach_discount/models/account_payment.py
odoo/addons/account_banking_ach_discount/models/account_payment_order.py
odoo/addons/account_banking_ach_discount/models/bank_payment_line.py
odoo/addons/account_banking_ach_discount/readme/CONFIGURE.rst
odoo/addons/account_banking_ach_discount/readme/CONTRIBUTORS.rst
odoo/addons/account_banking_ach_discount/readme/DESCRIPTION.rst
odoo/addons/account_banking_ach_discount/readme/HISTORY.rst
odoo/addons/account_banking_ach_discount/readme/USAGE.rst
odoo/addons/account_banking_ach_discount/static/description/icon.png
odoo/addons/account_banking_ach_discount/static/description/index.html
odoo/addons/account_banking_ach_discount/views/account_payment_view.xml
odoo/addons/account_banking_ach_discount/wizard/__init__.py
odoo/addons/account_banking_ach_discount/wizard/account_payment_register.py
odoo14_addon_account_banking_ach_discount-14.0.1.0.1.dev13.dist-info/METADATA
odoo14_addon_account_banking_ach_discount-14.0.1.0.1.dev13.dist-info/WHEEL
odoo14_addon_account_banking_ach_discount-14.0.1.0.1.dev13.dist-info/top_level.txt
odoo14_addon_account_banking_ach_discount-14.0.1.0.1.dev13.dist-info/RECORD
