Metadata-Version: 2.1
Name: odoo14-addon-account-banking-ach-discount
Version: 14.0.1.0.1.dev13
Summary: Discount on ACH batch payments
Home-page: https://github.com/OCA/l10n-usa
Author: Open Source Integrators, Odoo Community Association (OCA)
Author-email: support@odoo-community.org
License: AGPL-3
Platform: UNKNOWN
Classifier: Programming Language :: Python
Classifier: Framework :: Odoo
Classifier: Framework :: Odoo :: 14.0
Classifier: License :: OSI Approved :: GNU Affero General Public License v3
Classifier: Development Status :: 4 - Beta
Requires-Python: >=3.6
Requires-Dist: odoo14-addon-account-banking-ach-credit-transfer
Requires-Dist: odoo14-addon-account-banking-ach-direct-debit
Requires-Dist: odoo14-addon-account-payment-batch-process
Requires-Dist: odoo14-addon-account-payment-order
Requires-Dist: odoo14-addon-account-payment-term-discount
Requires-Dist: odoo <14.1dev,>=14.0a
